restish_auth/__init__.py
requests_restish_auth-0.2.dist-info/LICENSE
requests_restish_auth-0.2.dist-info/METADATA
requests_restish_auth-0.2.dist-info/WHEEL
requests_restish_auth-0.2.dist-info/top_level.txt
requests_restish_auth-0.2.dist-info/RECORD
