Metadata-Version: 2.1
Name: requests-restish-auth
Version: 0.2
Summary: Authenticate requests by shelling-out to restish for an OIDC flow
Author-email: Exoscale <support@exoscale.com>
License: Copyright 2022 Exoscale        
Project-URL: Homepage, https://github.com/exoscale/requests-restish-auth
Classifier: Programming Language :: Python :: 3
Classifier: License :: OSI Approved :: MIT License
Classifier: Operating System :: OS Independent
Requires-Python: >=3.7
License-File: LICENSE
